LICENSE
ansible_gendoc/__init__.py
ansible_gendoc/gendoc.py
ansible_gendoc/helpers.py
ansible_gendoc/main.py
ansible_gendoc/templates/README.j2
ansible_gendoc-0.1.11.dist-info/entry_points.txt
ansible_gendoc-0.1.11.dist-info/LICENSE
ansible_gendoc-0.1.11.dist-info/WHEEL
ansible_gendoc-0.1.11.dist-info/METADATA
ansible_gendoc-0.1.11.dist-info/RECORD
