Metadata-Version: 2.1
Name: ansible-gendoc
Version: 0.1.11
Summary: Ansible-gendoc build documentation of Ansible Roles.
Home-page: https://www.claranet.fr/
Keywords: ansible,role,documentation
Author: Stephane ROBERT
Author-email: stephane.robert@fr.clara.net
Requires-Python: >=3.10,<4.0
Classifier: Programming Language :: Python :: 3
Classifier: Programming Language :: Python :: 3.10
Requires-Dist: GitPython (>=3.1.27,<4.0.0)
Requires-Dist: Jinja2 (>=3.1.2,<4.0.0)
Requires-Dist: PyYAML (>=6.0,<7.0)
Requires-Dist: giturlparse (>=0.10.0,<0.11.0)
Requires-Dist: importlib-metadata (>=4.12.0,<5.0.0)
Requires-Dist: ruamel.yaml (>=0.17.21,<0.18.0)
Requires-Dist: typer[all] (>=0.6.1,<0.7.0)
Project-URL: Repository, https://github.com/claranet/ansible-gendoc
